pygcdm/__init__.py
pygcdm/netcdf_decode.py
pygcdm/netcdf_encode.py
pygcdm/netcdf_grpc.py
pygcdm/protogen/__init__.py
pygcdm/protogen/gcdm_grid_pb2.py
pygcdm/protogen/gcdm_grid_pb2_grpc.py
pygcdm/protogen/gcdm_netcdf_pb2.py
pygcdm/protogen/gcdm_netcdf_pb2_grpc.py
pygcdm/protogen/gcdm_server_pb2.py
pygcdm/protogen/gcdm_server_pb2_grpc.py
pygcdm-0.1.0.dist-info/LICENSE
pygcdm-0.1.0.dist-info/METADATA
pygcdm-0.1.0.dist-info/WHEEL
pygcdm-0.1.0.dist-info/top_level.txt
pygcdm-0.1.0.dist-info/RECORD
