Metadata-Version: 2.1
Name: pygcdm
Version: 0.1.0
Summary: Transfer CDM files using Remote Procedure Calls.
Home-page: https://github.com/rmcsqrd/pygcdm
Author: Rio McMahon
Author-email: rmcsqrd@gmail.com
License: BSD-3
Platform: UNKNOWN
Classifier: License :: OSI Approved :: BSD License
Classifier: Programming Language :: Python
Classifier: Programming Language :: Python :: 3
Classifier: Programming Language :: Python :: 3.9
Requires-Python: >=3.9.0
Requires-Dist: numpy
Requires-Dist: xarray
Requires-Dist: netCDF4
Requires-Dist: grpcio
Requires-Dist: grpcio-tools
